html_telegraph_poster_v2/__init__.py
html_telegraph_poster_v2/async_poster/__init__.py
html_telegraph_poster_v2/async_poster/converter.py
html_telegraph_poster_v2/async_poster/create_account.py
html_telegraph_poster_v2/async_poster/errors.py
html_telegraph_poster_v2/async_poster/html_to_telegraph.py
html_telegraph_poster_v2/async_poster/image_upload/__init__.py
html_telegraph_poster_v2/async_poster/image_upload/aws.py
html_telegraph_poster_v2/async_poster/image_upload/github.py
html_telegraph_poster_v2/async_poster/image_upload/image_uploader.py
html_telegraph_poster_v2/async_poster/image_upload/imgur.py
html_telegraph_poster_v2/async_poster/upload_images.py
html_telegraph_poster_v2/async_poster/utils.py
html_telegraph_poster_v2/config.py
html_telegraph_poster_v2/converter.py
html_telegraph_poster_v2/create_account.py
html_telegraph_poster_v2/errors.py
html_telegraph_poster_v2/html_to_telegraph.py
html_telegraph_poster_v2/upload_images.py
html_telegraph_poster_v2/utils/__init__.py
html_telegraph_poster_v2/utils/logger.py
html_telegraph_poster_v2/utils/parse.py
html_telegraph_poster_v2/utils.py
html_telegraph_poster_v2-0.2.5.dist-info/LICENSE
html_telegraph_poster_v2-0.2.5.dist-info/METADATA
html_telegraph_poster_v2-0.2.5.dist-info/WHEEL
html_telegraph_poster_v2-0.2.5.dist-info/RECORD
