Metadata-Version: 2.1
Name: html-telegraph-poster-v2
Version: 0.2.5
Summary: Upload HTML document to telegra.ph
License: MIT
Author: aturret
Author-email: enturreopy@gmail.com
Requires-Python: >=3.11,<4.0
Classifier: License :: OSI Approved :: MIT License
Classifier: Programming Language :: Python :: 3
Classifier: Programming Language :: Python :: 3.11
Classifier: Programming Language :: Python :: 3.12
Classifier: Programming Language :: Python :: 3.13
Requires-Dist: aioboto3 (>=13.2.0,<14.0.0)
Requires-Dist: aiofiles (>=24.1.0,<25.0.0)
Requires-Dist: httpx (>=0.27.0)
Requires-Dist: loguru (>=0.7.3,<0.8.0)
Requires-Dist: lxml[html-clean] (>=5.3.0,<6.0.0)
Requires-Dist: requests (>=2.26.0,<3.0.0)
Requires-Dist: requests_toolbelt (>=1.0.0,<2.0.0)
